{
  "project_info": {
    "project_number": "1037777161868",
    "project_id": "taskmanager-a3d7b",
    "storage_bucket": "taskmanager-a3d7b.appspot.com"
  },
  "client": [
    {
      "client_info": {
        "mobilesdk_app_id": "1:1037777161868:android:74a0a7e99ba24351d875a9",
        "android_client_info": {
          "package_name": "com.example.task_manager"
        }
      },
      "oauth_client": [{
        
      }],
      "api_key": [
        {
          "current_key": "AIzaSyDBaNczWQJDIt5NIVRCftvHa-knVTsBZGQ"
        }
      ],
      "services": {
        "appinvite_service": {
          "other_platform_oauth_client": []
        }
      }
    }
    
  ],
  "configuration_version": "1"
}